[
    {
        "title": "Nlw 05",
        "image": "block",
        "questionsAnswered": 1,
        "level": "facil",
        "questions": [
            {
                "title": "Está curtindo",
                "awnsers": [
                    {
                        "title": "estou curtindo"
                    },
                    {
                        "title": "nao"
                    },
                    {
                        "title": "da pro gasto"
                    },
                    {
                        "title": "otimo",
                        "isRight": true
                    }
                ]
            }
        ]
    }
]